Workbook

Sheet Dashboard
A1: Distributor ROI & Profitability Dashboard
A2: SIMULATED DATA — for portfolio demonstration only; not actual company/distributor results.
A4: Total Primary Sales | B4: =SUM(DistData!D2:D181) | C4: Average Profitability | D4: =AVERAGE(DistData!M2:M181) | E4: Average Annualised ROI | F4: =AVERAGE(DistData!N2:N181) | G4: Below Benchmark Rows | H4: =COUNTIF(DistData!Q2:Q181,"Below benchmark")
A7: Distributor Summary (12-month totals/averages)
A8: Distributor | B8: Region / Town | C8: Total Primary Sales (₹) | D8: Avg Profitability % | E8: Avg ROI % | F8: Avg Claim Settlement % | G8: Flag
A9: Hubli Traders | B9: Hubli | C9: =SUMIF(DistData!$A$2:$A$181,A9,DistData!$D$2:$D$181) | D9: =AVERAGEIF(DistData!$A$2:$A$181,A9,DistData!$M$2:$M$181) | E9: =AVERAGEIF(DistData!$A$2:$A$181,A9,DistData!$N$2:$N$181) | F9: =AVERAGEIF(DistData!$A$2:$A$181,A9,DistData!$O$2:$O$181) | G9: =IF(D9<0.06,"Below benchmark",IF(D9<=0.08,"On target","Strong"))
A10: Belagavi Distributors | B10: Belagavi | C10: =SUMIF(DistData!$A$2:$A$181,A10,DistData!$D$2:$D$181) | D10: =AVERAGEIF(DistData!$A$2:$A$181,A10,DistData!$M$2:$M$181) | E10: =AVERAGEIF(DistData!$A$2:$A$181,A10,DistData!$N$2:$N$181) | F10: =AVERAGEIF(DistData!$A$2:$A$181,A10,DistData!$O$2:$O$181) | G10: =IF(D10<0.06,"Below benchmark",IF(D10<=0.08,"On target","Strong"))
A11: Mysuru Wholesale | B11: Mysuru | C11: =SUMIF(DistData!$A$2:$A$181,A11,DistData!$D$2:$D$181) | D11: =AVERAGEIF(DistData!$A$2:$A$181,A11,DistData!$M$2:$M$181) | E11: =AVERAGEIF(DistData!$A$2:$A$181,A11,DistData!$N$2:$N$181) | F11: =AVERAGEIF(DistData!$A$2:$A$181,A11,DistData!$O$2:$O$181) | G11: =IF(D11<0.06,"Below benchmark",IF(D11<=0.08,"On target","Strong"))
A12: Mangaluru Agencies | B12: Mangaluru | C12: =SUMIF(DistData!$A$2:$A$181,A12,DistData!$D$2:$D$181) | D12: =AVERAGEIF(DistData!$A$2:$A$181,A12,DistData!$M$2:$M$181) | E12: =AVERAGEIF(DistData!$A$2:$A$181,A12,DistData!$N$2:$N$181) | F12: =AVERAGEIF(DistData!$A$2:$A$181,A12,DistData!$O$2:$O$181) | G12: =IF(D12<0.06,"Below benchmark",IF(D12<=0.08,"On target","Strong"))
A13: Dharwad Supply Co | B13: Dharwad | C13: =SUMIF(DistData!$A$2:$A$181,A13,DistData!$D$2:$D$181) | D13: =AVERAGEIF(DistData!$A$2:$A$181,A13,DistData!$M$2:$M$181) | E13: =AVERAGEIF(DistData!$A$2:$A$181,A13,DistData!$N$2:$N$181) | F13: =AVERAGEIF(DistData!$A$2:$A$181,A13,DistData!$O$2:$O$181) | G13: =IF(D13<0.06,"Below benchmark",IF(D13<=0.08,"On target","Strong"))
A14: Shivamogga Distributors | B14: Shivamogga | C14: =SUMIF(DistData!$A$2:$A$181,A14,DistData!$D$2:$D$181) | D14: =AVERAGEIF(DistData!$A$2:$A$181,A14,DistData!$M$2:$M$181) | E14: =AVERAGEIF(DistData!$A$2:$A$181,A14,DistData!$N$2:$N$181) | F14: =AVERAGEIF(DistData!$A$2:$A$181,A14,DistData!$O$2:$O$181) | G14: =IF(D14<0.06,"Below benchmark",IF(D14<=0.08,"On target","Strong"))
A15: Tumakuru Trade Links | B15: Tumakuru | C15: =SUMIF(DistData!$A$2:$A$181,A15,DistData!$D$2:$D$181) | D15: =AVERAGEIF(DistData!$A$2:$A$181,A15,DistData!$M$2:$M$181) | E15: =AVERAGEIF(DistData!$A$2:$A$181,A15,DistData!$N$2:$N$181) | F15: =AVERAGEIF(DistData!$A$2:$A$181,A15,DistData!$O$2:$O$181) | G15: =IF(D15<0.06,"Below benchmark",IF(D15<=0.08,"On target","Strong"))
A16: Udupi Sales Network | B16: Udupi | C16: =SUMIF(DistData!$A$2:$A$181,A16,DistData!$D$2:$D$181) | D16: =AVERAGEIF(DistData!$A$2:$A$181,A16,DistData!$M$2:$M$181) | E16: =AVERAGEIF(DistData!$A$2:$A$181,A16,DistData!$N$2:$N$181) | F16: =AVERAGEIF(DistData!$A$2:$A$181,A16,DistData!$O$2:$O$181) | G16: =IF(D16<0.06,"Below benchmark",IF(D16<=0.08,"On target","Strong"))
A17: Ballari Distributors | B17: Ballari | C17: =SUMIF(DistData!$A$2:$A$181,A17,DistData!$D$2:$D$181) | D17: =AVERAGEIF(DistData!$A$2:$A$181,A17,DistData!$M$2:$M$181) | E17: =AVERAGEIF(DistData!$A$2:$A$181,A17,DistData!$N$2:$N$181) | F17: =AVERAGEIF(DistData!$A$2:$A$181,A17,DistData!$O$2:$O$181) | G17: =IF(D17<0.06,"Below benchmark",IF(D17<=0.08,"On target","Strong"))
A18: Davangere Traders | B18: Davangere | C18: =SUMIF(DistData!$A$2:$A$181,A18,DistData!$D$2:$D$181) | D18: =AVERAGEIF(DistData!$A$2:$A$181,A18,DistData!$M$2:$M$181) | E18: =AVERAGEIF(DistData!$A$2:$A$181,A18,DistData!$N$2:$N$181) | F18: =AVERAGEIF(DistData!$A$2:$A$181,A18,DistData!$O$2:$O$181) | G18: =IF(D18<0.06,"Below benchmark",IF(D18<=0.08,"On target","Strong"))
A19: Kalaburagi Agencies | B19: Kalaburagi | C19: =SUMIF(DistData!$A$2:$A$181,A19,DistData!$D$2:$D$181) | D19: =AVERAGEIF(DistData!$A$2:$A$181,A19,DistData!$M$2:$M$181) | E19: =AVERAGEIF(DistData!$A$2:$A$181,A19,DistData!$N$2:$N$181) | F19: =AVERAGEIF(DistData!$A$2:$A$181,A19,DistData!$O$2:$O$181) | G19: =IF(D19<0.06,"Below benchmark",IF(D19<=0.08,"On target","Strong"))
A20: Hassan Wholesale | B20: Hassan | C20: =SUMIF(DistData!$A$2:$A$181,A20,DistData!$D$2:$D$181) | D20: =AVERAGEIF(DistData!$A$2:$A$181,A20,DistData!$M$2:$M$181) | E20: =AVERAGEIF(DistData!$A$2:$A$181,A20,DistData!$N$2:$N$181) | F20: =AVERAGEIF(DistData!$A$2:$A$181,A20,DistData!$O$2:$O$181) | G20: =IF(D20<0.06,"Below benchmark",IF(D20<=0.08,"On target","Strong"))
... A23: Mandya Trade House | B23: Mandya | C23: =SUMIF(DistData!$A$2:$A$181,A23,DistData!$D$2:$D$181) | D23: =AVERAGEIF(DistData!$A$2:$A$181,A23,DistData!$M$2:$M$181) | E23: =AVERAGEIF(DistData!$A$2:$A$181,A23,DistData!$N$2:$N$181) | F23: =AVERAGEIF(DistData!$A$2:$A$181,A23,DistData!$O$2:$O$181) | G23: =IF(D23<0.06,"Below benchmark",IF(D23<=0.08,"On target","Strong"))
A26: Monthly Sales Trend
A27: Month | B27: Primary Sales (₹) | C27: Secondary Sales (₹)
A28: 45748 | B28: =SUMIFS(DistData!$D$2:$D$181,DistData!$C$2:$C$181,A28) | C28: =SUMIFS(DistData!$E$2:$E$181,DistData!$C$2:$C$181,A28)
A29: 45778 | B29: =SUMIFS(DistData!$D$2:$D$181,DistData!$C$2:$C$181,A29) | C29: =SUMIFS(DistData!$E$2:$E$181,DistData!$C$2:$C$181,A29)
A30: 45809 | B30: =SUMIFS(DistData!$D$2:$D$181,DistData!$C$2:$C$181,A30) | C30: =SUMIFS(DistData!$E$2:$E$181,DistData!$C$2:$C$181,A30)
A31: 45839 | B31: =SUMIFS(DistData!$D$2:$D$181,DistData!$C$2:$C$181,A31) | C31: =SUMIFS(DistData!$E$2:$E$181,DistData!$C$2:$C$181,A31)
A32: 45870 | B32: =SUMIFS(DistData!$D$2:$D$181,DistData!$C$2:$C$181,A32) | C32: =SUMIFS(DistData!$E$2:$E$181,DistData!$C$2:$C$181,A32)
A33: 45901 | B33: =SUMIFS(DistData!$D$2:$D$181,DistData!$C$2:$C$181,A33) | C33: =SUMIFS(DistData!$E$2:$E$181,DistData!$C$2:$C$181,A33)
A34: 45931 | B34: =SUMIFS(DistData!$D$2:$D$181,DistData!$C$2:$C$181,A34) | C34: =SUMIFS(DistData!$E$2:$E$181,DistData!$C$2:$C$181,A34)
A35: 45962 | B35: =SUMIFS(DistData!$D$2:$D$181,DistData!$C$2:$C$181,A35) | C35: =SUMIFS(DistData!$E$2:$E$181,DistData!$C$2:$C$181,A35)
A36: 45992 | B36: =SUMIFS(DistData!$D$2:$D$181,DistData!$C$2:$C$181,A36) | C36: =SUMIFS(DistData!$E$2:$E$181,DistData!$C$2:$C$181,A36)
A37: 46023 | B37: =SUMIFS(DistData!$D$2:$D$181,DistData!$C$2:$C$181,A37) | C37: =SUMIFS(DistData!$E$2:$E$181,DistData!$C$2:$C$181,A37)
A38: 46054 | B38: =SUMIFS(DistData!$D$2:$D$181,DistData!$C$2:$C$181,A38) | C38: =SUMIFS(DistData!$E$2:$E$181,DistData!$C$2:$C$181,A38)
A39: 46082 | B39: =SUMIFS(DistData!$D$2:$D$181,DistData!$C$2:$C$181,A39) | C39: =SUMIFS(DistData!$E$2:$E$181,DistData!$C$2:$C$181,A39)
A42: Findings (validate after opening in Excel)
A43: Review the distributor summary for the lowest profitability and claim settlement rates. Investigate high operating costs, lower secondary sales versus primary sales, and delayed scheme claim settlement. All records are simulated; replace this text with findings from the workbook's actual calculated results.

Sheet DistData
A1: Distributor | B1: Region / Town | C1: Month | D1: Primary Sales (₹) | E1: Secondary Sales (₹) | F1: Margin % | G1: Scheme Claims Raised (₹) | H1: Scheme Claims Settled (₹) | I1: Operating Cost (₹) | J1: Investment (₹) | K1: Gross Margin (₹) | L1: Net Profit (₹) | M1: Profitability % | N1: ROI % (annualised) | O1: Claim Settlement % | P1: Primary vs Secondary Gap (₹) | Q1: Flag
A2: Hubli Traders | B2: Hubli | C2: 45748 | D2: 966739 | E2: 795629 | F2: 0.050250108 | G2: 52314 | H2: 23431 | I2: 68358 | J2: 985929 | K2: =D2*F2 | L2: =K2+H2-I2 | M2: =IFERROR(L2/D2,0) | N2: =IFERROR((L2*12)/J2,0) | O2: =IFERROR(H2/G2,0) | P2: =D2-E2 | Q2: =IF(M2<0.06,"Below benchmark",IF(M2<=0.08,"On target","Strong"))
A3: Hubli Traders | B3: Hubli | C3: 45778 | D3: 941161 | E3: 747106 | F3: 0.055904925 | G3: 48070 | H3: 22291 | I3: 81559 | J3: 713912 | K3: =D3*F3 | L3: =K3+H3-I3 | M3: =IFERROR(L3/D3,0) | N3: =IFERROR((L3*12)/J3,0) | O3: =IFERROR(H3/G3,0) | P3: =D3-E3 | Q3: =IF(M3<0.06,"Below benchmark",IF(M3<=0.08,"On target","Strong"))
A4: Hubli Traders | B4: Hubli | C4: 45809 | D4: 1438508 | E4: 1248604 | F4: 0.051988377 | G4: 62856 | H4: 31673 | I4: 79719 | J4: 845852 | K4: =D4*F4 | L4: =K4+H4-I4 | M4: =IFERROR(L4/D4,0) | N4: =IFERROR((L4*12)/J4,0) | O4: =IFERROR(H4/G4,0) | P4: =D4-E4 | Q4: =IF(M4<0.06,"Below benchmark",IF(M4<=0.08,"On target","Strong"))
A5: Hubli Traders | B5: Hubli | C5: 45839 | D5: 856814 | E5: 693298 | F5: 0.057588074 | G5: 58848 | H5: 28720 | I5: 70094 | J5: 812886 | K5: =D5*F5 | L5: =K5+H5-I5 | M5: =IFERROR(L5/D5,0) | N5: =IFERROR((L5*12)/J5,0) | O5: =IFERROR(H5/G5,0) | P5: =D5-E5 | Q5: =IF(M5<0.06,"Below benchmark",IF(M5<=0.08,"On target","Strong"))
A6: Hubli Traders | B6: Hubli | C6: 45870 | D6: 1202944 | E6: 1005169 | F6: 0.051022103 | G6: 56763 | H6: 33461 | I6: 84782 | J6: 838685 | K6: =D6*F6 | L6: =K6+H6-I6 | M6: =IFERROR(L6/D6,0) | N6: =IFERROR((L6*12)/J6,0) | O6: =IFERROR(H6/G6,0) | P6: =D6-E6 | Q6: =IF(M6<0.06,"Below benchmark",IF(M6<=0.08,"On target","Strong"))
A7: Hubli Traders | B7: Hubli | C7: 45901 | D7: 895561 | E7: 765120 | F7: 0.057297318 | G7: 57403 | H7: 25013 | I7: 74606 | J7: 889600 | K7: =D7*F7 | L7: =K7+H7-I7 | M7: =IFERROR(L7/D7,0) | N7: =IFERROR((L7*12)/J7,0) | O7: =IFERROR(H7/G7,0) | P7: =D7-E7 | Q7: =IF(M7<0.06,"Below benchmark",IF(M7<=0.08,"On target","Strong"))
A8: Hubli Traders | B8: Hubli | C8: 45931 | D8: 1051629 | E8: 836569 | F8: 0.057045718 | G8: 52467 | H8: 30148 | I8: 67614 | J8: 822049 | K8: =D8*F8 | L8: =K8+H8-I8 | M8: =IFERROR(L8/D8,0) | N8: =IFERROR((L8*12)/J8,0) | O8: =IFERROR(H8/G8,0) | P8: =D8-E8 | Q8: =IF(M8<0.06,"Below benchmark",IF(M8<=0.08,"On target","Strong"))
A9: Hubli Traders | B9: Hubli | C9: 45962 | D9: 955907 | E9: 807176 | F9: 0.053801262 | G9: 72332 | H9: 35657 | I9: 77130 | J9: 886264 | K9: =D9*F9 | L9: =K9+H9-I9 | M9: =IFERROR(L9/D9,0) | N9: =IFERROR((L9*12)/J9,0) | O9: =IFERROR(H9/G9,0) | P9: =D9-E9 | Q9: =IF(M9<0.06,"Below benchmark",IF(M9<=0.08,"On target","Strong"))
A10: Hubli Traders | B10: Hubli | C10: 45992 | D10: 1069684 | E10: 935137 | F10: 0.056701752 | G10: 67398 | H10: 37042 | I10: 84960 | J10: 789725 | K10: =D10*F10 | L10: =K10+H10-I10 | M10: =IFERROR(L10/D10,0) | N10: =IFERROR((L10*12)/J10,0) | O10: =IFERROR(H10/G10,0) | P10: =D10-E10 | Q10: =IF(M10<0.06,"Below benchmark",IF(M10<=0.08,"On target","Strong"))
A11: Hubli Traders | B11: Hubli | C11: 46023 | D11: 1410086 | E11: 1141617 | F11: 0.057291268 | G11: 57433 | H11: 27222 | I11: 85971 | J11: 992002 | K11: =D11*F11 | L11: =K11+H11-I11 | M11: =IFERROR(L11/D11,0) | N11: =IFERROR((L11*12)/J11,0) | O11: =IFERROR(H11/G11,0) | P11: =D11-E11 | Q11: =IF(M11<0.06,"Below benchmark",IF(M11<=0.08,"On target","Strong"))
A12: Hubli Traders | B12: Hubli | C12: 46054 | D12: 1080283 | E12: 962685 | F12: 0.056846143 | G12: 70427 | H12: 30367 | I12: 91928 | J12: 716829 | K12: =D12*F12 | L12: =K12+H12-I12 | M12: =IFERROR(L12/D12,0) | N12: =IFERROR((L12*12)/J12,0) | O12: =IFERROR(H12/G12,0) | P12: =D12-E12 | Q12: =IF(M12<0.06,"Below benchmark",IF(M12<=0.08,"On target","Strong"))
A13: Hubli Traders | B13: Hubli | C13: 46082 | D13: 1180776 | E13: 942191 | F13: 0.054011648 | G13: 74921 | H13: 45595 | I13: 93716 | J13: 864981 | K13: =D13*F13 | L13: =K13+H13-I13 | M13: =IFERROR(L13/D13,0) | N13: =IFERROR((L13*12)/J13,0) | O13: =IFERROR(H13/G13,0) | P13: =D13-E13 | Q13: =IF(M13<0.06,"Below benchmark",IF(M13<=0.08,"On target","Strong"))
... A181: Mandya Trade House | B181: Mandya | C181: 46082 | D181: 1428116 | E181: 1312941 | F181: 0.075812599 | G181: 39796 | H181: 37135 | I181: 38559 | J181: 627697 | K181: =D181*F181 | L181: =K181+H181-I181 | M181: =IFERROR(L181/D181,0) | N181: =IFERROR((L181*12)/J181,0) | O181: =IFERROR(H181/G181,0) | P181: =D181-E181 | Q181: =IF(M181<0.06,"Below benchmark",IF(M181<=0.08,"On target","Strong"))

Sheet README
A1: Project README — Distributor ROI Dashboard
A3: Important disclosure | B3: All data in this workbook is simulated sample data created for a portfolio project. It does not represent actual company or distributor performance.
A4: Project objective | B4: Track distributor primary sales, secondary sales, margin, scheme claims, operating costs, profitability and annualised ROI.
A5: Calculated fields | B5: Gross Margin = Primary Sales × Margin %. Net Profit = Gross Margin + Claims Settled − Operating Cost. Profitability % = Net Profit ÷ Primary Sales. Annualised ROI = (Net Profit × 12) ÷ Investment. Claim Settlement % = Claims Settled ÷ Claims Raised. Primary vs Secondary Gap = Primary − Secondary.
A6: Benchmark | B6: Below 6% = Below benchmark; 6% through 8% = On target; above 8% = Strong. This is a project assumption based on the brief.
A7: Tools | B7: Microsoft Excel tables, formulas, conditional formatting and charts. Power Query / Power Pivot / slicers are not preconfigured in this generated workbook.
A8: Suggested next steps | B8: Open in Excel and allow formulas to recalculate; review dashboard; add PivotTables and slicers if required; take a screenshot; upload workbook and screenshot to GitHub.
A9: Resume bullet | B9: Built a distributor-wise dashboard of primary sales, margin, claims and ROI on simulated data; flagged distributors below the 6% profitability threshold and recommended corrective actions.
